aiodataloader.py
aiodataloader_ng-0.2.1.dist-info/LICENSE
aiodataloader_ng-0.2.1.dist-info/METADATA
aiodataloader_ng-0.2.1.dist-info/WHEEL
aiodataloader_ng-0.2.1.dist-info/top_level.txt
aiodataloader_ng-0.2.1.dist-info/RECORD
