Metadata-Version: 2.1
Name: aiodataloader-ng
Version: 0.2.1
Summary: Asyncio DataLoader implementation for Python
Home-page: https://github.com/lablup/aiodataloader-ng
Author: Syrus Akbary, Joongi Kim and other contributors
Author-email: joongi@lablup.com
License: MIT
Download-URL: https://github.com/lablup/aiodataloader/releases
Keywords: concurrent future deferred aiodataloader
Platform: UNKNOWN
Classifier: Development Status :: 5 - Production/Stable
Classifier: Intended Audience :: Developers
Classifier: Topic :: Software Development :: Libraries
Classifier: Programming Language :: Python :: 3
Classifier: Programming Language :: Python :: 3.8
Classifier: Programming Language :: Python :: 3.9
Classifier: Programming Language :: Python :: 3.10
Classifier: License :: OSI Approved :: MIT License
License-File: LICENSE
Provides-Extra: build
Requires-Dist: wheel (>=0.37.1) ; extra == 'build'
Requires-Dist: twine (>=3.7.1) ; extra == 'build'
Provides-Extra: lint
Requires-Dist: flake8 (>=3.9.0) ; extra == 'lint'
Provides-Extra: test
Requires-Dist: pytest (>=6.2.5) ; extra == 'test'
Requires-Dist: pytest-cov ; extra == 'test'
Requires-Dist: coveralls ; extra == 'test'
Requires-Dist: mock ; extra == 'test'
Requires-Dist: pytest-asyncio ; extra == 'test'
Provides-Extra: typecheck
Requires-Dist: mypy (>=0.930) ; extra == 'typecheck'
